vat_pytorch/__init__.py
vat_pytorch/alice.py
vat_pytorch/alicepp.py
vat_pytorch/smart.py
vat_pytorch/utils.py
vat_pytorch/models/__init__.py
vat_pytorch/models/alice_classification_model.py
vat_pytorch/models/alicepp_classification_model.py
vat_pytorch/models/extracted_model.py
vat_pytorch/models/extracted_roberta.py
vat_pytorch/models/smart_classification_model.py
vat_pytorch-0.0.9.dist-info/LICENSE
vat_pytorch-0.0.9.dist-info/METADATA
vat_pytorch-0.0.9.dist-info/WHEEL
vat_pytorch-0.0.9.dist-info/top_level.txt
vat_pytorch-0.0.9.dist-info/RECORD
