Metadata-Version: 2.1
Name: vat-pytorch
Version: 0.0.9
Summary: Virtual Adversarial Training - Pytorch
Home-page: https://github.com/archinetai/vat-pytorch
Author: Archinet
Author-email: archinetai@protonmail.com
License: MIT
Keywords: artificial intelligence,deep learning,fine-tuning,pre-trained
Classifier: Development Status :: 4 - Beta
Classifier: Intended Audience :: Developers
Classifier: Topic :: Scientific/Engineering :: Artificial Intelligence
Classifier: License :: OSI Approved :: MIT License
Classifier: Programming Language :: Python :: 3.6
License-File: LICENSE
Requires-Dist: torch (>=1.6)
Requires-Dist: data-science-types (>=0.2transformers>=4.0.0)
